bank/__init__.py
bank/getbanks.py
nigeria_bank_algos-0.1.1.dist-info/LICENCE
nigeria_bank_algos-0.1.1.dist-info/METADATA
nigeria_bank_algos-0.1.1.dist-info/WHEEL
nigeria_bank_algos-0.1.1.dist-info/top_level.txt
nigeria_bank_algos-0.1.1.dist-info/RECORD
