Metadata-Version: 2.1
Name: nigeria-bank-algos
Version: 0.1.1
Summary: A small bank algorithm that predict nigeria bank
Home-page: https://github.com/samkayz/nigeria-bank-algo.git
Author: Samson Ilemobayo
Author-email: ilemobayosamson@gmail.com
License: UNKNOWN
Platform: UNKNOWN
Classifier: Programming Language :: Python :: 3
Classifier: License :: OSI Approved :: MIT License
Classifier: Operating System :: OS Independent
Requires-Python: >=3.6
